Workbook

Sheet Assumptions
B2: FAIRWAY GOLF CLUB — Model Assumptions
B3: Blue values = inputs you can change to run scenarios
B5: PERSONAL INCOME
B6: Current OTE (W-2 salary + commission) | C6: 227000 | D6: Russell's current comp
B7: Annual raise assumption | C7: 0.03 | D7: Conservative 3% annual
B8: Estimated effective tax rate | C8: 0.38 | D8: Federal + VA state + FICA on W-2
B10: BUSINESS — PHASE 1 (2 BAYS)
B11: Number of bays (Phase 1) | C11: 2 | D11: Starting configuration
B12: Operating hours per day | C12: 12 | D12: 10am–10pm
B13: Days open per year | C13: 360 | D13: 5 days closed/maintenance
B14: Hourly rate (blended avg) | C14: 55 | D14: Mix: walk-in $65, member $40, off-peak $45
B15: Year 1 avg utilization | C15: 0.35 | D15: Ramp from 20% to 50% over 12 months
B16: Year 2 avg utilization | C16: 0.5 | D16: Steady state, mature 2-bay operation
B17: Year 3+ avg utilization (orig bays) | C17: 0.55 | D17: Slight growth from reputation
B19: ANCILLARY REVENUE (as % of bay revenue)
B20: Memberships / AI coaching premium | C20: 0.12 | D20: Recurring revenue above bay hours
B21: Beverage / bar revenue | C21: 0.08 | D21: ABC license + Bunny Man partnership
B22: Events / corporate / merch / leagues | C22: 0.05 | D22: Corporate nights, tournaments
B24: MONTHLY OPERATING COSTS
B25: Rent to Workhouse | C25: 3500 | D25: Negotiate; could be $3K-$4.5K
B26: Part-time staff (2 employees) | C26: 4800 | D26: 2×25hrs/wk×$18/hr + 15% burden
B27: Utilities (electric, HVAC, internet) | C27: 1200 | D27: Sims draw power; good HVAC needed
B28: Insurance (GL + property) | C28: 500 | D28: Commercial policy
B29: Software / sim subscriptions | C29: 600 | D29: Trackman/FullSwing subs, Salesforce
B30: Marketing / digital ads | C30: 800 | D30: Google, social, local sponsorships
B31: Supplies / maintenance / misc | C31: 500 | D31: Balls, tees, cleaning, bulbs
B32: ABC license (amortized monthly) | C32: 200 | D32: ~$2,400 one-time / 12 months
B34: FINANCING
B35: Total startup capital needed | C35: 150000 | D35: Phase 1 value-engineered budget
B36: Owner equity (personal investment) | C36: 75000 | D36: Cash from savings
B37: Loan amount (SBA or bank) | C37: 75000 | D37: Financed portion
B38: Loan interest rate (annual) | C38: 0.08 | D38: SBA 7(a) typical rate
B39: Loan term (years) | C39: 5 | D39: 60-month term
B41: PHASE 2 EXPANSION (begins Year 3)
B42: Additional bays | C42: 2 | D42: Expand from 2 → 4 total
B43: Phase 2 capital required | C43: 70000 | D43: Sims + bay buildout only
B44: Phase 2 loan amount | C44: 70000 | D44: Finance 100% from cash flow or loan
B45: Phase 2 new bays Year 1 utilization | C45: 0.4 | D45: Ramp faster (brand established)
B46: Phase 2 new bays steady state util | C46: 0.55 | D46: Match original bays
B47: Phase 2 incremental monthly costs | C47: 1800 | D47: Extra power, sim subs, add'l staff hrs

Sheet 5-Year Projection
B2: 5-YEAR HOUSEHOLD INCOME PROJECTION
B3: Keep day job + Fairway as side business → evaluate full-time at Phase 2
C5: Year 1 | D5: Year 2 | E5: Year 3 | F5: Year 4 | G5: Year 5
B6: YOUR W-2 INCOME
B7: Day job OTE (pre-tax) | C7: =Assumptions!C6*(1+Assumptions!C7)^0 -> 227000 | D7: =Assumptions!C6*(1+Assumptions!C7)^1 -> 233810 | E7: =Assumptions!C6*(1+Assumptions!C7)^2 -> 240824.3 | F7: =Assumptions!C6*(1+Assumptions!C7)^3 -> 248049.03 | G7: =Assumptions!C6*(1+Assumptions!C7)^4 -> 255490.5
B8: Day job after-tax take-home | C8: =C7*(1-Assumptions!C8) -> 140740 | D8: =D7*(1-Assumptions!C8) -> 144962.2 | E8: =E7*(1-Assumptions!C8) -> 149311.07 | F8: =F7*(1-Assumptions!C8) -> 153790.4 | G8: =G7*(1-Assumptions!C8) -> 158404.11
B10: FAIRWAY GOLF CLUB
B11: Operating bays | C11: =Assumptions!C11 -> 2 | D11: =Assumptions!C11 -> 2 | E11: =Assumptions!C11+Assumptions!C42 -> 4 | F11: =Assumptions!C11+Assumptions!C42 -> 4 | G11: =Assumptions!C11+Assumptions!C42 -> 4
B12: Avg utilization (blended) | C12: =Assumptions!C15 -> 0.35 | D12: =Assumptions!C16 -> 0.5 | E12: =(Assumptions!C11*Assumptions!C17+Assumptions!C42*Assumptions!C45)/(Assumptions!C11+Assumptions!C42) -> 0.475 | F12: =(Assumptions!C11*Assumptions!C17+Assumptions!C42*Assumptions!C46)/(Assumptions!C11+Assumptions!C42) -> 0.55 | G12: =Assumptions!C46 -> 0.55
B13: Bay rental revenue | C13: =C11*Assumptions!C12*Assumptions!C13*Assumptions!C14*C12 -> 166320 | D13: =D11*Assumptions!C12*Assumptions!C13*Assumptions!C14*D12 -> 237600 | E13: =E11*Assumptions!C12*Assumptions!C13*Assumptions!C14*E12 -> 451440 | F13: =F11*Assumptions!C12*Assumptions!C13*Assumptions!C14*F12 -> 522720 | G13: =G11*Assumptions!C12*Assumptions!C13*Assumptions!C14*G12 -> 522720
B14: Ancillary revenue (members, bar, events) | C14: =C13*(Assumptions!C20+Assumptions!C21+Assumptions!C22) -> 41580 | D14: =D13*(Assumptions!C20+Assumptions!C21+Assumptions!C22) -> 59400 | E14: =E13*(Assumptions!C20+Assumptions!C21+Assumptions!C22) -> 112860 | F14: =F13*(Assumptions!C20+Assumptions!C21+Assumptions!C22) -> 130680 | G14: =G13*(Assumptions!C20+Assumptions!C21+Assumptions!C22) -> 130680
B15: Total Fairway Revenue | C15: =C13+C14 -> 207900 | D15: =D13+D14 -> 297000 | E15: =E13+E14 -> 564300 | F15: =F13+F14 -> 653400 | G15: =G13+G14 -> 653400
B17: Operating costs (annual) | C17: =(Assumptions!C25+Assumptions!C26+Assumptions!C27+Assumptions!C28+Assumptions!C29+Assumptions!C30+Assumptions!C31+Assumptions!C32)*12 -> 145200 | D17: =(Assumptions!C25+Assumptions!C26+Assumptions!C27+Assumptions!C28+Assumptions!C29+Assumptions!C30+Assumptions!C31+Assumptions!C32)*12 -> 145200 | E17: =((Assumptions!C25+Assumptions!C26+Assumptions!C27+Assumptions!C28+Assumptions!C29+Assumptions!C30+Assumptions!C31+Assumptions!C32)+Assumptions!C47)*12 -> 166800 | F17: =((Assumptions!C25+Assumptions!C26+Assumptions!C27+Assumptions!C28+Assumptions!C29+Assumptions!C30+Assumptions!C31+Assumptions!C32)+Assumptions!C47)*12 -> 166800 | G17: =((Assumptions!C25+Assumptions!C26+Assumptions!C27+Assumptions!C28+Assumptions!C29+Assumptions!C30+Assumptions!C31+Assumptions!C32)+Assumptions!C47)*12 -> 166800
B18: Loan payments (annual P&I) | C18: =PMT(Assumptions!C38/12,Assumptions!C39*12,-Assumptions!C37)*12 -> 18248.755 | D18: =PMT(Assumptions!C38/12,Assumptions!C39*12,-Assumptions!C37)*12 -> 18248.755 | E18: =PMT(Assumptions!C38/12,Assumptions!C39*12,-Assumptions!C37)*12+PMT(Assumptions!C38/12,Assumptions!C39*12,-Assumptions!C44)*12 -> 35280.926 | F18: =PMT(Assumptions!C38/12,Assumptions!C39*12,-Assumptions!C37)*12+PMT(Assumptions!C38/12,Assumptions!C39*12,-Assumptions!C44)*12 -> 35280.926 | G18: =PMT(Assumptions!C38/12,Assumptions!C39*12,-Assumptions!C37)*12+PMT(Assumptions!C38/12,Assumptions!C39*12,-Assumptions!C44)*12 -> 35280.926
B19: Total Fairway Costs | C19: =C17+C18 -> 163448.75 | D19: =D17+D18 -> 163448.75 | E19: =E17+E18 -> 202080.93 | F19: =F17+F18 -> 202080.93 | G19: =G17+G18 -> 202080.93
B21: FAIRWAY NET PROFIT (pre-tax) | C21: =C15-C19 -> 44451.245 | D21: =D15-D19 -> 133551.25 | E21: =E15-E19 -> 362219.07 | F21: =F15-F19 -> 451319.07 | G21: =G15-G19 -> 451319.07
B22: → Monthly average | C22: =C21/12 -> 3704.2704 | D22: =D21/12 -> 11129.27 | E22: =E21/12 -> 30184.923 | F22: =F21/12 -> 37609.923 | G22: =G21/12 -> 37609.923
B24: COMBINED HOUSEHOLD
B25: Day Job + Fairway (pre-tax total) | C25: =C7+C21 -> 271451.25 | D25: =D7+D21 -> 367361.25 | E25: =E7+E21 -> 603043.37 | F25: =F7+F21 -> 699368.1 | G25: =G7+G21 -> 706809.57
B26: Surplus vs. day job alone | C26: =C21 -> 44451.245 | D26: =D21 -> 133551.25 | E26: =E21 -> 362219.07 | F26: =F21 -> 451319.07 | G26: =G21 -> 451319.07
B28: IF RUSSELL QUITS: Fairway-only income | C28: =C21 -> 44451.245 | D28: =D21 -> 133551.25 | E28: =E21 -> 362219.07 | F28: =F21 -> 451319.07 | G28: =G21 -> 451319.07
B29: → Gap vs. current $227K OTE | C29: =C28-Assumptions!C6 -> -182548.75 | D29: =D28-Assumptions!C6 -> -93448.755 | E29: =E28-Assumptions!C6 -> 135219.07 | F29: =F28-Assumptions!C6 -> 224319.07 | G29: =G28-Assumptions!C6 -> 224319.07
B30: → Ready to quit day job? | C30: =IF(C28>=Assumptions!C6,"YES - Fairway alone covers OTE","Not yet - keep day job") -> Not yet - keep day job | D30: =IF(D28>=Assumptions!C6,"YES - Fairway alone covers OTE","Not yet - keep day job") -> Not yet - keep day job | E30: =IF(E28>=Assumptions!C6,"YES - Fairway alone covers OTE","Not yet - keep day job") -> YES - Fairway alone covers OTE | F30: =IF(F28>=Assumptions!C6,"YES - Fairway alone covers OTE","Not yet - keep day job") -> YES - Fairway alone covers OTE | G30: =IF(G28>=Assumptions!C6,"YES - Fairway alone covers OTE","Not yet - keep day job") -> YES - Fairway alone covers OTE
B32: WEALTH BUILDING
B33: Cumulative Fairway net profit | C33: =C21 -> 44451.245 | D33: =C33+D21 -> 178002.49 | E33: =D33+E21 -> 540221.56 | F33: =E33+F21 -> 991540.64 | G33: =F33+G21 -> 1442859.7
B34: Personal equity ($75K) recovered? | C34: =IF(C33>=Assumptions!C36,"YES - equity recovered","Not yet") -> Not yet | D34: =IF(D33>=Assumptions!C36,"YES - equity recovered","Not yet") -> YES - equity recovered | E34: =IF(E33>=Assumptions!C36,"YES - equity recovered","Not yet") -> YES - equity recovered | F34: =IF(F33>=Assumptions!C36,"YES - equity recovered","Not yet") -> YES - equity recovered | G34: =IF(G33>=Assumptions!C36,"YES - equity recovered","Not yet") -> YES - equity recovered
B35: Est. business value (3× annual profit) | C35: =MAX(0,C21*3) -> 133353.74 | D35: =MAX(0,D21*3) -> 400653.74 | E35: =MAX(0,E21*3) -> 1086657.2 | F35: =MAX(0,F21*3) -> 1353957.2 | G35: =MAX(0,G21*3) -> 1353957.2
B36: Total new wealth created (cumulative + value) | C36: =C33+C35 -> 177804.98 | D36: =D33+D35 -> 578656.23 | E36: =E33+E35 -> 1626878.8 | F36: =F33+F35 -> 2345497.9 | G36: =G33+G35 -> 2796816.9

Sheet Year 1 Monthly
B2: YEAR 1 MONTHLY — The Realistic Ramp
B3: Day job continues. Fairway ramps from soft-open to steady state.
C5: Mo 1 | D5: Mo 2 | E5: Mo 3 | F5: Mo 4 | G5: Mo 5 | H5: Mo 6 | I5: Mo 7 | J5: Mo 8 | K5: Mo 9 | L5: Mo 10 | M5: Mo 11 | N5: Mo 12 | O5: TOTAL
B6: INCOME (Day Job)
B7: W-2 monthly (pre-tax) | C7: =Assumptions!C6/12 -> 18916.667 | D7: =Assumptions!C6/12 -> 18916.667 | E7: =Assumptions!C6/12 -> 18916.667 | F7: =Assumptions!C6/12 -> 18916.667 | G7: =Assumptions!C6/12 -> 18916.667 | H7: =Assumptions!C6/12 -> 18916.667 | I7: =Assumptions!C6/12 -> 18916.667 | J7: =Assumptions!C6/12 -> 18916.667 | K7: =Assumptions!C6/12 -> 18916.667 | L7: =Assumptions!C6/12 -> 18916.667 | M7: =Assumptions!C6/12 -> 18916.667 | N7: =Assumptions!C6/12 -> 18916.667 | O7: =SUM(C7:N7) -> 227000
B8: W-2 after-tax take-home | C8: =C7*(1-Assumptions!C8) -> 11728.333 | D8: =D7*(1-Assumptions!C8) -> 11728.333 | E8: =E7*(1-Assumptions!C8) -> 11728.333 | F8: =F7*(1-Assumptions!C8) -> 11728.333 | G8: =G7*(1-Assumptions!C8) -> 11728.333 | H8: =H7*(1-Assumptions!C8) -> 11728.333 | I8: =I7*(1-Assumptions!C8) -> 11728.333 | J8: =J7*(1-Assumptions!C8) -> 11728.333 | K8: =K7*(1-Assumptions!C8) -> 11728.333 | L8: =L7*(1-Assumptions!C8) -> 11728.333 | M8: =M7*(1-Assumptions!C8) -> 11728.333 | N8: =N7*(1-Assumptions!C8) -> 11728.333 | O8: =SUM(C8:N8) -> 140740
B10: FAIRWAY REVENUE
B11: Bay utilization | C11: 0.2 | D11: 0.25 | E11: 0.28 | F11: 0.32 | G11: 0.35 | H11: 0.38 | I11: 0.4 | J11: 0.43 | K11: 0.45 | L11: 0.48 | M11: 0.5 | N11: 0.52
B12: Bay rental revenue | C12: =Assumptions!C11*Assumptions!C12*30*Assumptions!C14*C11 -> 7920 | D12: =Assumptions!C11*Assumptions!C12*30*Assumptions!C14*D11 -> 9900 | E12: =Assumptions!C11*Assumptions!C12*30*Assumptions!C14*E11 -> 11088 | F12: =Assumptions!C11*Assumptions!C12*30*Assumptions!C14*F11 -> 12672 | G12: =Assumptions!C11*Assumptions!C12*30*Assumptions!C14*G11 -> 13860 | H12: =Assumptions!C11*Assumptions!C12*30*Assumptions!C14*H11 -> 15048 | I12: =Assumptions!C11*Assumptions!C12*30*Assumptions!C14*I11 -> 15840 | J12: =Assumptions!C11*Assumptions!C12*30*Assumptions!C14*J11 -> 17028 | K12: =Assumptions!C11*Assumptions!C12*30*Assumptions!C14*K11 -> 17820 | L12: =Assumptions!C11*Assumptions!C12*30*Assumptions!C14*L11 -> 19008 | M12: =Assumptions!C11*Assumptions!C12*30*Assumptions!C14*M11 -> 19800 | N12: =Assumptions!C11*Assumptions!C12*30*Assumptions!C14*N11 -> 20592 | O12: =SUM(C12:N12) -> 180576
B13: Ancillary revenue | C13: =C12*(Assumptions!C20+Assumptions!C21+Assumptions!C22) -> 1980 | D13: =D12*(Assumptions!C20+Assumptions!C21+Assumptions!C22) -> 2475 | E13: =E12*(Assumptions!C20+Assumptions!C21+Assumptions!C22) -> 2772 | F13: =F12*(Assumptions!C20+Assumptions!C21+Assumptions!C22) -> 3168 | G13: =G12*(Assumptions!C20+Assumptions!C21+Assumptions!C22) -> 3465 | H13: =H12*(Assumptions!C20+Assumptions!C21+Assumptions!C22) -> 3762 | I13: =I12*(Assumptions!C20+Assumptions!C21+Assumptions!C22) -> 3960 | J13: =J12*(Assumptions!C20+Assumptions!C21+Assumptions!C22) -> 4257 | K13: =K12*(Assumptions!C20+Assumptions!C21+Assumptions!C22) -> 4455 | L13: =L12*(Assumptions!C20+Assumptions!C21+Assumptions!C22) -> 4752 | M13: =M12*(Assumptions!C20+Assumptions!C21+Assumptions!C22) -> 4950 | N13: =N12*(Assumptions!C20+Assumptions!C21+Assumptions!C22) -> 5148 | O13: =SUM(C13:N13) -> 45144
B14: Total Fairway monthly revenue | C14: =C12+C13 -> 9900 | D14: =D12+D13 -> 12375 | E14: =E12+E13 -> 13860 | F14: =F12+F13 -> 15840 | G14: =G12+G13 -> 17325 | H14: =H12+H13 -> 18810 | I14: =I12+I13 -> 19800 | J14: =J12+J13 -> 21285 | ... N14: =N12+N13 -> 25740 | O14: =SUM(C14:N14) -> 225720
B16: FAIRWAY COSTS
B17: Operating costs | C17: =(Assumptions!C25+Assumptions!C26+Assumptions!C27+Assumptions!C28+Assumptions!C29+Assumptions!C30+Assumptions!C31+Assumptions!C32) -> 12100 | D17: =(Assumptions!C25+Assumptions!C26+Assumptions!C27+Assumptions!C28+Assumptions!C29+Assumptions!C30+Assumptions!C31+Assumptions!C32) -> 12100 | E17: =(Assumptions!C25+Assumptions!C26+Assumptions!C27+Assumptions!C28+Assumptions!C29+Assumptions!C30+Assumptions!C31+Assumptions!C32) -> 12100 | F17: =(Assumptions!C25+Assumptions!C26+Assumptions!C27+Assumptions!C28+Assumptions!C29+Assumptions!C30+Assumptions!C31+Assumptions!C32) -> 12100 | G17: =(Assumptions!C25+Assumptions!C26+Assumptions!C27+Assumptions!C28+Assumptions!C29+Assumptions!C30+Assumptions!C31+Assumptions!C32) -> 12100 | H17: =(Assumptions!C25+Assumptions!C26+Assumptions!C27+Assumptions!C28+Assumptions!C29+Assumptions!C30+Assumptions!C31+Assumptions!C32) -> 12100 | I17: =(Assumptions!C25+Assumptions!C26+Assumptions!C27+Assumptions!C28+Assumptions!C29+Assumptions!C30+Assumptions!C31+Assumptions!C32) -> 12100 | J17: =(Assumptions!C25+Assumptions!C26+Assumptions!C27+Assumptions!C28+Assumptions!C29+Assumptions!C30+Assumptions!C31+Assumptions!C32) -> 12100 | K17: =(Assumptions!C25+Assumptions!C26+Assumptions!C27+Assumptions!C28+Assumptions!C29+Assumptions!C30+Assumptions!C31+Assumptions!C32) -> 12100 | L17: =(Assumptions!C25+Assumptions!C26+Assumptions!C27+Assumptions!C28+Assumptions!C29+Assumptions!C30+Assumptions!C31+Assumptions!C32) -> 12100 | M17: =(Assumptions!C25+Assumptions!C26+Assumptions!C27+Assumptions!C28+Assumptions!C29+Assumptions!C30+Assumptions!C31+Assumptions!C32) -> 12100 | N17: =(Assumptions!C25+Assumptions!C26+Assumptions!C27+Assumptions!C28+Assumptions!C29+Assumptions!C30+Assumptions!C31+Assumptions!C32) -> 12100 | O17: =SUM(C17:N17) -> 145200
B18: Loan payment (monthly) | C18: =PMT(Assumptions!C38/12,Assumptions!C39*12,-Assumptions!C37) -> 1520.7296 | D18: =PMT(Assumptions!C38/12,Assumptions!C39*12,-Assumptions!C37) -> 1520.7296 | E18: =PMT(Assumptions!C38/12,Assumptions!C39*12,-Assumptions!C37) -> 1520.7296 | F18: =PMT(Assumptions!C38/12,Assumptions!C39*12,-Assumptions!C37) -> 1520.7296 | G18: =PMT(Assumptions!C38/12,Assumptions!C39*12,-Assumptions!C37) -> 1520.7296 | H18: =PMT(Assumptions!C38/12,Assumptions!C39*12,-Assumptions!C37) -> 1520.7296 | I18: =PMT(Assumptions!C38/12,Assumptions!C39*12,-Assumptions!C37) -> 1520.7296 | J18: =PMT(Assumptions!C38/12,Assumptions!C39*12,-Assumptions!C37) -> 1520.7296 | K18: =PMT(Assumptions!C38/12,Assumptions!C39*12,-Assumptions!C37) -> 1520.7296 | L18: =PMT(Assumptions!C38/12,Assumptions!C39*12,-Assumptions!C37) -> 1520.7296 | M18: =PMT(Assumptions!C38/12,Assumptions!C39*12,-Assumptions!C37) -> 1520.7296 | N18: =PMT(Assumptions!C38/12,Assumptions!C39*12,-Assumptions!C37) -> 1520.7296 | O18: =SUM(C18:N18) -> 18248.755
B19: Total Fairway costs | C19: =C17+C18 -> 13620.73 | D19: =D17+D18 -> 13620.73 | E19: =E17+E18 -> 13620.73 | F19: =F17+F18 -> 13620.73 | G19: =G17+G18 -> 13620.73 | H19: =H17+H18 -> 13620.73 | I19: =I17+I18 -> 13620.73 | J19: =J17+J18 -> 13620.73 | ... N19: =N17+N18 -> 13620.73 | O19: =SUM(C19:N19) -> 163448.75
B21: FAIRWAY MONTHLY NET PROFIT | C21: =C14-C19 -> -3720.7296 | D21: =D14-D19 -> -1245.7296 | E21: =E14-E19 -> 239.27043 | F21: =F14-F19 -> 2219.2704 | G21: =G14-G19 -> 3704.2704 | H21: =H14-H19 -> 5189.2704 | I21: =I14-I19 -> 6179.2704 | J21: =J14-J19 -> 7664.2704 | ... N21: =N14-N19 -> 12119.27 | O21: =SUM(C21:N21) -> 62271.245
B23: HOUSEHOLD MONTHLY CASH
B24: Day job take-home | C24: =C8 -> 11728.333 | D24: =D8 -> 11728.333 | E24: =E8 -> 11728.333 | F24: =F8 -> 11728.333 | G24: =G8 -> 11728.333 | H24: =H8 -> 11728.333 | I24: =I8 -> 11728.333 | J24: =J8 -> 11728.333 | ... N24: =N8 -> 11728.333 | O24: =SUM(C24:N24) -> 140740
B25: Fairway net contribution | C25: =C21 -> -3720.7296 | D25: =D21 -> -1245.7296 | E25: =E21 -> 239.27043 | F25: =F21 -> 2219.2704 | G25: =G21 -> 3704.2704 | H25: =H21 -> 5189.2704 | I25: =I21 -> 6179.2704 | J25: =J21 -> 7664.2704 | ... N25: =N21 -> 12119.27 | O25: =SUM(C25:N25) -> 62271.245
B26: Total household monthly cash | C26: =C24+C25 -> 8007.6038 | D26: =D24+D25 -> 10482.604 | E26: =E24+E25 -> 11967.604 | F26: =F24+F25 -> 13947.604 | G26: =G24+G25 -> 15432.604 | H26: =H24+H25 -> 16917.604 | I26: =I24+I25 -> 17907.604 | J26: =J24+J25 -> 19392.604 | ... N26: =N24+N25 -> 23847.604 | O26: =SUM(C26:N26) -> 203011.25
B28: SAFETY NET
B29: If Fairway makes $0 this month, you still have: | C29: =C8 -> 11728.333 | D29: =D8 -> 11728.333 | E29: =E8 -> 11728.333 | F29: =F8 -> 11728.333 | G29: =G8 -> 11728.333 | H29: =H8 -> 11728.333 | I29: =I8 -> 11728.333 | J29: =J8 -> 11728.333 | ... N29: =N8 -> 11728.333 | O29: =SUM(C29:N29) -> 140740

Sheet The Pitch
B2: FAIRWAY GOLF CLUB — The Case for Our Family
B3: Bottom line: We keep our income. This adds to it. Here's how.
B5: THE PLAN
B6: Russell keeps his $227K/yr day job — no income change
B7: 2 part-time staff run Fairway during the day ($18/hr)
B8: Russell closes up evenings (~9-10pm) — lives 1 mile away
B9: Household income stays the same. Fairway profit is ADDITIVE.
B11: WHAT WE RISK
B12: Personal cash invested: | C12: =Assumptions!C36 -> 75000
B13: Monthly loan payment: | C13: =PMT(Assumptions!C38/12,Assumptions!C39*12,-Assumptions!C37) -> 1520.7296
B14: Russell's evenings for close-up (~1 hr/night)
B15: If entire business fails, total loss = equity invested (like a car)
B17: WHAT WE GAIN EACH YEAR (added to household)
B18: Year 1 — Fairway adds to household: | C18: ='5-Year Projection'!C21 -> 44451.245
B19: Year 2 — Fairway adds: | C19: ='5-Year Projection'!D21 -> 133551.25
B20: Year 3 — Expand to 4 bays, adds: | C20: ='5-Year Projection'!E21 -> 362219.07
B21: Year 4 — Steady 4-bay operation, adds: | C21: ='5-Year Projection'!F21 -> 451319.07
B22: Year 5 — Mature operation, adds: | C22: ='5-Year Projection'!G21 -> 451319.07
B24: YEAR 5 TOTAL HOUSEHOLD INCOME: | C24: ='5-Year Projection'!G25 -> 706809.57
B25: vs. Day Job alone in Year 5: | C25: ='5-Year Projection'!G7 -> 255490.5
B27: THE SAFETY NET
B28: If Fairway earns $0, household still earns: | C28: =Assumptions!C6 -> 227000
B29: Worst case total loss (personal equity): | C29: =Assumptions!C36 -> 75000
B30: That's less than one new car. And we own the equipment as assets.
B32: THE UPSIDE (Year 5)
B33: Business estimated value (sellable): | C33: ='5-Year Projection'!G35 -> 1353957.2
B34: Cumulative profits earned: | C34: ='5-Year Projection'!G33 -> 1442859.7
B35: Total new household wealth created: | C35: ='5-Year Projection'!G36 -> 2796816.9
B37: WHEN COULD RUSSELL QUIT?
B38: Fairway alone covers $227K: Year 4-5 (4 bays at 55%)
B39: Recommended: keep day job through Year 2, evaluate at expansion
B40: Best case: quit Year 3 if utilization consistently >55%
B41: No pressure — the business works AS A SIDE INCOME indefinitely
